hybrid_django_react/__init__.py
hybrid_django_react/assets/.flake8
hybrid_django_react/assets/.vscode/launch.json
hybrid_django_react/assets/.vscode/settings.json
hybrid_django_react/assets/Dockerfile
hybrid_django_react/assets/Dockerfile_frontend
hybrid_django_react/assets/docker-compose.yml
hybrid_django_react/assets/frontend/App.js
hybrid_django_react/assets/frontend/components/forms/Radio/Radio.js
hybrid_django_react/assets/frontend/components/forms/Radio/Radio.stories.js
hybrid_django_react/assets/frontend/components/forms/Radio/Radio.styles.js
hybrid_django_react/assets/frontend/components/forms/Radio/Radio.test.js
hybrid_django_react/assets/frontend/components/forms/Select/Select.js
hybrid_django_react/assets/frontend/components/forms/Select/Select.stories.js
hybrid_django_react/assets/frontend/components/forms/Select/Select.styles.js
hybrid_django_react/assets/frontend/components/forms/Select/Select.test.js
hybrid_django_react/assets/frontend/components/forms/TextField/TextField.js
hybrid_django_react/assets/frontend/components/forms/TextField/TextField.stories.js
hybrid_django_react/assets/frontend/components/forms/TextField/TextField.styles.js
hybrid_django_react/assets/frontend/components/forms/TextField/TextField.test.js
hybrid_django_react/assets/frontend/components/forms/index.js
hybrid_django_react/assets/frontend/components/layout/index.js
hybrid_django_react/assets/frontend/components/layout/navigation/NavBar/NavBar.js
hybrid_django_react/assets/frontend/components/layout/navigation/NavBar/NavBar.stories.js
hybrid_django_react/assets/frontend/components/layout/navigation/NavBar/NavBar.styles.js
hybrid_django_react/assets/frontend/components/layout/navigation/NavBar/NavBar.test.js
hybrid_django_react/assets/frontend/index.js
hybrid_django_react/assets/frontend/services/LocalStorage/LocalStorage.service.js
hybrid_django_react/assets/frontend/services/LocalStorage/LocalStorage.test.js
hybrid_django_react/assets/frontend/services/index.js
hybrid_django_react-0.2.2.dist-info/entry_points.txt
hybrid_django_react-0.2.2.dist-info/LICENSE
hybrid_django_react-0.2.2.dist-info/WHEEL
hybrid_django_react-0.2.2.dist-info/METADATA
hybrid_django_react-0.2.2.dist-info/RECORD
