Metadata-Version: 2.1
Name: hybrid-django-react
Version: 0.2.2
Summary: Django starter project template. Dockerized Django serving a static React app
Home-page: https://github.com/gmso/hybrid-django-react
License: MIT
Keywords: Django,React,Starter project
Author: gmso
Author-email: german.mene@gmail.com
Requires-Python: >=3.7,<4.0
Classifier: Framework :: Django
Classifier: License :: OSI Approved :: MIT License
Classifier: Operating System :: OS Independent
Classifier: Programming Language :: Python :: 3
Classifier: Programming Language :: Python :: 3.10
Classifier: Programming Language :: Python :: 3.7
Classifier: Programming Language :: Python :: 3.8
Classifier: Programming Language :: Python :: 3.9
